argutils/__init__.py
argutils/export.py
argutils/read.py
argutils-0.3.3.dist-info/METADATA
argutils-0.3.3.dist-info/WHEEL
argutils-0.3.3.dist-info/top_level.txt
argutils-0.3.3.dist-info/RECORD
