Metadata-Version: 2.1
Name: argutils
Version: 0.3.3
Summary: Functions to build matched argument parsers and config files
Home-page: https://github.com/eclarke/argutils
Author: Erik Clarke
Author-email: ecl@mail.med.upenn.edu
License: GPLv2+
Platform: UNKNOWN
Classifier: License :: OSI Approved :: GNU General Public License v2 or later (GPLv2+)
Classifier: Operating System :: POSIX :: Linux
Classifier: Operating System :: MacOS :: MacOS X
Classifier: Programming Language :: Python :: 2.7
Classifier: Programming Language :: Python :: 3
Classifier: Topic :: Software Development
Classifier: Topic :: Utilities
Requires-Dist: six
Requires-Dist: pyyaml
